LICENSE.txt
setup.cfg
setup.py
discord_bot_manager/__init__.py
discord_bot_manager.egg-info/PKG-INFO
discord_bot_manager.egg-info/SOURCES.txt
discord_bot_manager.egg-info/dependency_links.txt
discord_bot_manager.egg-info/requires.txt
discord_bot_manager.egg-info/top_level.txt
discord_bot_manager/commands/__init__.py
discord_bot_manager/commands/command.py
discord_bot_manager/commands/discord.py
discord_bot_manager/commands/types.py
discord_bot_manager/commands/user_commands/__init__.py
discord_bot_manager/commands/user_commands/ai.py
discord_bot_manager/commands/user_commands/utils.py
discord_bot_manager/utils/__init__.py
discord_bot_manager/utils/config.py
discord_bot_manager/utils/formatter.py
discord_bot_manager/utils/search.py