Metadata-Version: 1.1
Name: discord-bot-manager
Version: 1.0.0
Summary: TYPE YOUR DESCRIPTION HERE
Home-page: https://github.com/vaskrneup/DiscordBot
Author: YOUR NAME
Author-email: vaskrneup@gmail.com
License: MIT
Keywords: discord,bot,manager
Platform: UNKNOWN
Classifier: License :: OSI Approved :: MIT License
Classifier: Programming Language :: Python :: 3
Classifier: Programming Language :: Python :: 3.7
